alpha_vantage_cli/__init__.py
alpha_vantage_cli/cli.py
alpha_vantage_cli/factory.py
alpha_vantage_cli/options.py
alpha_vantage_cli-0.1.2.dist-info/entry_points.txt
alpha_vantage_cli-0.1.2.dist-info/WHEEL
alpha_vantage_cli-0.1.2.dist-info/METADATA
alpha_vantage_cli-0.1.2.dist-info/RECORD
