Metadata-Version: 2.1
Name: alpha-vantage-cli
Version: 0.1.2
Summary: 
License: MIT
Author: Omar Sosa Rodriguez
Author-email: omarfsosa@gmail.com
Requires-Python: >=3.10,<4.0
Classifier: License :: OSI Approved :: MIT License
Classifier: Programming Language :: Python :: 3
Classifier: Programming Language :: Python :: 3.10
Requires-Dist: click (>=8.1.3,<9.0.0)
Requires-Dist: requests (>=2.28.1,<3.0.0)
